enthalpy_estimator/__init__.py
enthalpy_estimator/cfg.py
enthalpy_estimator/generator.py
enthalpy_estimator/rgen.dll
enthalpy_estimator/rgen.so
enthalpy_estimator/simple_vectorizer.py
enthalpy_estimator/single_reaction.py
enthalpy_estimator/smiles_vectorizer.py
enthalpy_estimator-1.dist-info/LICENSE
enthalpy_estimator-1.dist-info/METADATA
enthalpy_estimator-1.dist-info/WHEEL
enthalpy_estimator-1.dist-info/RECORD
