Metadata-Version: 2.1
Name: enthalpy_estimator
Version: 1
Summary: A package to automatically generate reactions and estimate enthalpy.
License: GNU General Public License v3.0
Author: Egor Nosach
Requires-Python: >=3.10
Classifier: License :: Other/Proprietary License
Classifier: Programming Language :: Python :: 3
Classifier: Programming Language :: Python :: 3.10
Classifier: Programming Language :: Python :: 3.11
Classifier: Programming Language :: Python :: 3.12
Requires-Dist: numpy (>=1.26)
Requires-Dist: scipy (>=1.14)
